alu.v
module alu(a,b,f,y);
  input[31:0]a,b;
  input[2:0]f;
  output[31:0]y;
  reg[31:0]y;
  always @ (a,b,f)
    begin
    case(f)
      3'b000:y=a+b;
      3'b001:y=a-b;
      3'b010:y=a*b;
      3'b011:y=a/b;
      3'b100:y=a&b;
      3'b101:y=a|b;
      3'b110:y=~a;
      3'b111:y=~(a+b);
    endcase
  end
endmodule

alutb.v
module alutb;
reg [31:0] a,b;
reg[2:0]f;
wire [31:0]y;
alu uut(a,b,f,y);
initial
begin
$dumpfile("alu.vcd");
$dumpvars(0,alutb);
a=32'h1234AB00;
b=32'h4321AB11;
f=3'b000;#10;//ADD
f=3'b001;#10;//SUB
f=3'b011;#10;//DIV
f=3'b100;#10;//AND
f=3'b101;#10;//OR
f=3'b110;#10;//NOT A
f=3'b111;#10;//~(A+B)
a=32'h00001234;
b=32'h00004321;
f=3'b010;#10;
$finish;
end
initial begin
$monitor ("Time=%0t|f=%b|a=%h|b=%h|y=%h",$time,f,a,b,y);
end
endmodule

alu.vcd
$date
	Sun Sep 27 19:54:21 2026
$end
$version
	Icarus Verilog
$end
$timescale
	1s
$end
$scope module alutb $end
$var wire 32 ! y [31:0] $end
$var reg 32 " a [31:0] $end
$var reg 32 # b [31:0] $end
$var reg 3 $ f [2:0] $end
$scope module uut $end
$var wire 32 % a [31:0] $end
$var wire 32 & b [31:0] $end
$var wire 3 ' f [2:0] $end
$var reg 32 ( y [31:0] $end
$upscope $end
$upscope $end
$enddefinitions $end
$comment Show the parameter values. $end
$dumpall
$end
#0
$dumpvars
b1010101010101100101011000010001 (
b0 '
b1000011001000011010101100010001 &
b10010001101001010101100000000 %
b0 $
b1000011001000011010101100010001 #
b10010001101001010101100000000 "
b1010101010101100101011000010001 !
$end
#10
b11001111000100101111111111101111 !
b11001111000100101111111111101111 (
b1 $
b1 '
#20
b0 !
b0 (
b11 $
b11 '
#30
b10001000001010101100000000 !
b10001000001010101100000000 (
b100 $
b100 '
#40
b1010011001101011010101100010001 !
b1010011001101011010101100010001 (
b101 $
b101 '
#50
b11101101110010110101010011111111 !
b11101101110010110101010011111111 (
b110 $
b110 '
#60
b10101010101010011010100111101110 !
b10101010101010011010100111101110 (
b111 $
b111 '
#70
b100110001011111010010110100 !
b100110001011111010010110100 (
b10 $
b10 '
b100001100100001 #
b100001100100001 &
b1001000110100 "
b1001000110100 %
