traffic.v
module taffic #(
  parameter RED=3'b100,
           GREEN=3'b010,
  YELLOW=3'b001)//FSM states 
  (input clk,rst,
    output reg [2:0]cur_state,
   output  reg[3:0]count);
  always @(posedge clk)
    begin
      if(rst)//active-high reset
        begin
          cur_state<=RED;//current state is RED
         count<=0;//reset count
        end
      else//reset is inactive
        begin
          count<=count+1;//increment count
          case(cur_state)//case statement for current state
           
            RED: //when current state is RED
              begin   
                if(count==9)//when count reaches 9 current state changes from RED to GREEN
                begin
              cur_state<=GREEN;//RED to GREEN
                count<=0;//reset count
                end
         end
              GREEN://when current state is GREEN
                begin
                  if(count==9)//wait till count reaches 9
                begin
                cur_state<=YELLOW;//GREEN to YELLOW 
                count<=0;// reset count
                end
              end
              
              YELLOW://current state is YELLOW
                begin
                  if(count==2)//wait till count reaches 2
                begin
                cur_state<=RED;//YELLOW to RED
                count<=0;// reset count
                end
              end
          endcase//end of case statement
        end
    end
      endmodule

traffic_tb.v
module traffic_signal_tb;

  reg clk,rst;
  wire[2:0]cur_state;
  wire [3:0]count;
  taffic  uut(.clk(clk),.rst(rst),.cur_state(cur_state),.count(count));
  always #5 clk=~clk;
  initial
    begin
      $dumpfile("traffic.vcd");
      $dumpvars(0,traffic_signal_tb);
      $monitor("clk=%b rst=%d cur_state=%d count=%d",clk,rst,cur_state,count);
      clk=0;rst=1;
      
               
      #15;rst=0;
      #200;$finish;
    end
endmodule

traffic.vcd
$date
	Sun Oct  4 19:19:15 2026
$end
$version
	Icarus Verilog
$end
$timescale
	1s
$end
$scope module traffic_signal_tb $end
$var wire 3 ! cur_state [2:0] $end
$var wire 4 " count [3:0] $end
$var reg 1 # clk $end
$var reg 1 $ rst $end
$scope module uut $end
$var wire 1 # clk $end
$var wire 1 $ rst $end
$var parameter 3 % GREEN $end
$var parameter 3 & RED $end
$var parameter 3 ' YELLOW $end
$var reg 4 ( count [3:0] $end
$var reg 3 ) cur_state [2:0] $end
$upscope $end
$upscope $end
$enddefinitions $end
$comment Show the parameter values. $end
$dumpall
b1 '
b100 &
b10 %
$end
#0
$dumpvars
bx )
bx (
1$
0#
bx "
bx !
$end
#5
b0 "
b0 (
b100 !
b100 )
1#
#10
0#
#15
b1 "
b1 (
1#
0$
#20
0#
#25
b10 "
b10 (
1#
#30
0#
#35
b11 "
b11 (
1#
#40
0#
#45
b100 "
b100 (
1#
#50
0#
#55
b101 "
b101 (
1#
#60
0#
#65
b110 "
b110 (
1#
#70
0#
#75
b111 "
b111 (
1#
#80
0#
#85
b1000 "
b1000 (
1#
#90
0#
#95
b1001 "
b1001 (
1#
#100
0#
#105
b10 !
b10 )
b0 "
b0 (
1#
#110
0#
#115
b1 "
b1 (
1#
#120
0#
#125
b10 "
b10 (
1#
#130
0#
#135
b11 "
b11 (
1#
#140
0#
#145
b100 "
b100 (
1#
#150
0#
#155
b101 "
b101 (
1#
#160
0#
#165
b110 "
b110 (
1#
#170
0#
#175
b111 "
b111 (
1#
#180
0#
#185
b1000 "
b1000 (
1#
#190
0#
#195
b1001 "
b1001 (
1#
#200
0#
#205
b1 !
b1 )
b0 "
b0 (
1#
#210
0#
#215
b1 "
b1 (
1#
